{"61335": {"expansion_id": -1, "expansion": "Unknown (-1)", "points": 0, "criteria": [{"index": 1, "id": 216907, "desc": "Eversong Woods"}, {"index": 2, "id": 216910, "desc": "Harandar"}, {"index": 3, "id": 216906, "desc": "Silvermoon City"}, {"index": 4, "id": 216909, "desc": "Voidstorm"}, {"index": 5, "id": 216908, "desc": "Zul'Aman"}]}, "61336": {"expansion_id": -1, "expansion": "Unknown (-1)", "points": 0, "criteria": [{"index": 1, "id": 216913, "desc": "Eversong Woods"}, {"index": 2, "id": 216916, "desc": "Harandar"}, {"index": 3, "id": 216912, "desc": "Silvermoon City"}, {"index": 4, "id": 216915, "desc": "Voidstorm"}, {"index": 5, "id": 216914, "desc": "Zul'Aman"}]}, "61442": {"expansion_id": -1, "expansion": "Unknown (-1)", "points": 0, "criteria": []}, "61463": {"expansion_id": -1, "expansion": "Unknown (-1)", "points": 0, "criteria": [{"index": 1, "id": 218589, "desc": "Gain Mastery of Timeways for 5 weeks during Turbulent Timeways V"}]}, "62413": {"expansion_id": -1, "expansion": "Unknown (-1)", "points": 0, "criteria": [{"index": 1, "id": 224064, "desc": "Legacy of the Amani"}, {"index": 2, "id": 224065, "desc": "An Island of Fangs"}, {"index": 3, "id": 224066, "desc": "Ghosts of the Past"}, {"index": 4, "id": 224067, "desc": "Original Sin"}, {"index": 5, "id": 224068, "desc": "The Battle for Atal'Utek"}]}, "62606": {"expansion_id": -1, "expansion": "Unknown (-1)", "points": 0, "criteria": []}, "62842": {"expansion_id": -1, "expansion": "Unknown (-1)", "points": 0, "criteria": [{"index": 1, "id": 225721, "desc": "Evade 100 lightning strikes in a row."}]}, "62873": {"expansion_id": -1, "expansion": "Unknown (-1)", "points": 0, "criteria": [{"index": 1, "id": 229951, "desc": "Into the Stars"}, {"index": 2, "id": 229952, "desc": "Prepared for a Showdown"}, {"index": 3, "id": 229953, "desc": "Frosty Domanaar Politics"}, {"index": 4, "id": 229954, "desc": "Climate Strange: Val"}, {"index": 5, "id": 229955, "desc": "Showdown Slugger: Val"}, {"index": 6, "id": 229956, "desc": "Showdown Success: Val"}]}, "62874": {"expansion_id": -1, "expansion": "Unknown (-1)", "points": 0, "criteria": [{"index": 1, "id": 229957, "desc": "Into the Stars"}, {"index": 2, "id": 229958, "desc": "Prepared for a Showdown"}, {"index": 3, "id": 229959, "desc": "A Hal'hadar Walks into a Swamp"}, {"index": 4, "id": 229960, "desc": "Climate Strange: Naigtal"}, {"index": 5, "id": 229961, "desc": "Showdown Slugger: Naigtal"}, {"index": 6, "id": 229962, "desc": "Showdown Success: Naigtal"}]}, "62880": {"expansion_id": -1, "expansion": "Unknown (-1)", "points": 0, "criteria": [{"index": 1, "id": 227373, "desc": "Lingering Corruption"}, {"index": 2, "id": 227374, "desc": "Freeze Range Eggs"}, {"index": 3, "id": 227375, "desc": "A Lingering Echo"}, {"index": 4, "id": 227376, "desc": "Ignoble Gas Collector"}, {"index": 5, "id": 227377, "desc": "Junction Dysfunction"}, {"index": 6, "id": 227378, "desc": "Solid Cold"}, {"index": 7, "id": 227379, "desc": "Shadowy Strategies"}, {"index": 8, "id": 227380, "desc": "Dissent and Divide"}, {"index": 9, "id": 227381, "desc": "Cold Reception"}, {"index": 10, "id": 227382, "desc": "Tainted Ritual"}, {"index": 11, "id": 227383, "desc": "Until it is Done"}, {"index": 12, "id": 227384, "desc": "Aberration Liberation"}, {"index": 13, "id": 227385, "desc": "Caver Saviour"}, {"index": 14, "id": 227386, "desc": "One Friend is Plenty"}]}, "62881": {"expansion_id": -1, "expansion": "Unknown (-1)", "points": 0, "criteria": [{"index": 1, "id": 227388, "desc": "Sleet-Rune"}, {"index": 2, "id": 227389, "desc": "Atomus"}, {"index": 3, "id": 227390, "desc": "Glacial Broodmother"}, {"index": 4, "id": 227391, "desc": "Mercilus"}, {"index": 5, "id": 227392, "desc": "Xirah"}, {"index": 6, "id": 227393, "desc": "Krilkan"}, {"index": 7, "id": 227394, "desc": "Opprimius"}, {"index": 8, "id": 227395, "desc": "Nelgothar"}, {"index": 9, "id": 227396, "desc": "The Horror Below"}, {"index": 10, "id": 227397, "desc": "Shadowguard Destroyer"}]}, "62882": {"expansion_id": -1, "expansion": "Unknown (-1)", "points": 0, "criteria": [{"index": 1, "id": 227408, "desc": "Mush-Vroom!"}, {"index": 2, "id": 227409, "desc": "Mashing Mushroom Mana Machines"}, {"index": 3, "id": 227410, "desc": "Scrubbing Troubles"}, {"index": 4, "id": 227412, "desc": "Power Overload"}, {"index": 5, "id": 227413, "desc": "Sporadic Power Drain"}, {"index": 6, "id": 227414, "desc": "Marsh Mana Spores"}, {"index": 7, "id": 227415, "desc": "Skiff Joyride"}, {"index": 8, "id": 227416, "desc": "Forest Mana Spores"}, {"index": 9, "id": 227461, "desc": "Crypt Culling"}, {"index": 10, "id": 227462, "desc": "Weaken Their Forces"}, {"index": 11, "id": 229602, "desc": "Capsized Compost"}, {"index": 12, "id": 231463, "desc": "Flying Debris"}]}, "62883": {"expansion_id": -1, "expansion": "Unknown (-1)", "points": 0, "criteria": [{"index": 1, "id": 227400, "desc": "Interminable Uarn"}, {"index": 2, "id": 227401, "desc": "Broxion"}, {"index": 3, "id": 227402, "desc": "Swalewing Matriarch"}, {"index": 4, "id": 227403, "desc": "Lomelith"}, {"index": 5, "id": 227404, "desc": "Auredar"}, {"index": 6, "id": 227405, "desc": "Warp Agent Xi'grivr"}, {"index": 7, "id": 227406, "desc": "Indomitable Mk XII"}, {"index": 8, "id": 227407, "desc": "Slaipaan"}]}, "62887": {"expansion_id": -1, "expansion": "Unknown (-1)", "points": 0, "criteria": [{"index": 1, "id": 227464, "desc": "Mush-Vroom!"}, {"index": 2, "id": 227465, "desc": "Mashing Mushroom Mana Machines"}, {"index": 3, "id": 227466, "desc": "Scrubbing Troubles"}, {"index": 4, "id": 227468, "desc": "Power Overload"}, {"index": 5, "id": 227469, "desc": "Sporadic Power Drain"}, {"index": 6, "id": 227470, "desc": "Marsh Mana Spores"}, {"index": 7, "id": 227471, "desc": "Skiff Joyride"}, {"index": 8, "id": 227472, "desc": "Forest Mana Spores"}, {"index": 9, "id": 227473, "desc": "Crypt Culling"}, {"index": 10, "id": 227474, "desc": "Weaken Their Forces"}, {"index": 11, "id": 227475, "desc": "Lingering Corruption"}, {"index": 12, "id": 227476, "desc": "Freeze Range Eggs"}, {"index": 13, "id": 227477, "desc": "A Lingering Echo"}, {"index": 14, "id": 227478, "desc": "Ignoble Gas Collector"}, {"index": 15, "id": 227479, "desc": "Junction Dysfunction"}, {"index": 16, "id": 227480, "desc": "Solid Cold"}, {"index": 17, "id": 227481, "desc": "Shadowy Strategies"}, {"index": 18, "id": 227482, "desc": "Dissent and Divide"}, {"index": 19, "id": 227483, "desc": "Cold Reception"}, {"index": 20, "id": 227484, "desc": "Tainted Ritual"}, {"index": 21, "id": 227485, "desc": "Until it is Done"}, {"index": 22, "id": 227486, "desc": "Aberration Liberation"}, {"index": 23, "id": 227487, "desc": "Caver Saviour"}, {"index": 24, "id": 227488, "desc": "One Friend is Plenty"}, {"index": 25, "id": 231462, "desc": "Flying Debris"}]}, "62901": {"expansion_id": -1, "expansion": "Unknown (-1)", "points": 0, "criteria": [{"index": 1, "id": 227556, "desc": "Arcane Presence"}, {"index": 2, "id": 227557, "desc": "Blood Infusion"}, {"index": 3, "id": 227558, "desc": "Brutal Presence"}, {"index": 4, "id": 227559, "desc": "Curse Infusion"}, {"index": 5, "id": 227560, "desc": "Disease Infusion"}, {"index": 6, "id": 227561, "desc": "Enrage Infusion"}, {"index": 7, "id": 227562, "desc": "Magic Infusion"}, {"index": 8, "id": 227563, "desc": "Poison Infusion"}, {"index": 9, "id": 227564, "desc": "Snare Infusion"}, {"index": 10, "id": 227565, "desc": "Swift Presence"}, {"index": 11, "id": 227566, "desc": "Vigorous Presence"}, {"index": 12, "id": 227567, "desc": "Essence Balance"}, {"index": 13, "id": 227568, "desc": "Steam Vents"}, {"index": 14, "id": 227569, "desc": "Bouncy Mushroom"}, {"index": 15, "id": 227570, "desc": "Mana Overload"}, {"index": 16, "id": 227571, "desc": "Cosmic Horror"}, {"index": 17, "id": 227572, "desc": "Glacial Spike"}, {"index": 18, "id": 227573, "desc": "Spiraling Quasar"}, {"index": 19, "id": 227574, "desc": "Thorny Vine"}, {"index": 20, "id": 227576, "desc": "Arcane Sacrifice"}, {"index": 21, "id": 227577, "desc": "Shadow Strikes"}, {"index": 22, "id": 227578, "desc": "Sleeping Gas"}, {"index": 23, "id": 227579, "desc": "Ice Shield"}, {"index": 24, "id": 227580, "desc": "Mycelium Network"}, {"index": 25, "id": 227581, "desc": "Chill Touched"}, {"index": 26, "id": 227582, "desc": "Gravity Shackles"}, {"index": 27, "id": 227583, "desc": "Void Shields"}, {"index": 28, "id": 227584, "desc": "Icy Beam"}, {"index": 29, "id": 227585, "desc": "Phase Stepping"}, {"index": 30, "id": 227586, "desc": "Unraveling"}, {"index": 31, "id": 227587, "desc": "Voidmaw"}, {"index": 32, "id": 227588, "desc": "Cosmic Tethers"}, {"index": 33, "id": 227589, "desc": "Mystery Mushroom"}, {"index": 34, "id": 227590, "desc": "Frozen Core"}, {"index": 35, "id": 227591, "desc": "Infested"}]}, "62903": {"expansion_id": -1, "expansion": "Unknown (-1)", "points": 0, "criteria": []}, "62904": {"expansion_id": -1, "expansion": "Unknown (-1)", "points": 0, "criteria": []}, "62905": {"expansion_id": -1, "expansion": "Unknown (-1)", "points": 0, "criteria": [{"index": 1, "id": 227657, "desc": "Imperator Pertinax"}, {"index": 2, "id": 227658, "desc": "Nexus-Captain Leth'ir"}]}, "62909": {"expansion_id": -1, "expansion": "Unknown (-1)", "points": 0, "criteria": [{"index": 1, "id": 227660, "desc": "Imperator Pertinax"}, {"index": 2, "id": 227661, "desc": "Nexus-Captain Leth'ir"}]}, "62917": {"expansion_id": -1, "expansion": "Unknown (-1)", "points": 0, "criteria": []}, "62919": {"expansion_id": -1, "expansion": "Unknown (-1)", "points": 0, "criteria": []}, "62940": {"expansion_id": -1, "expansion": "Unknown (-1)", "points": 0, "criteria": []}, "62941": {"expansion_id": -1, "expansion": "Unknown (-1)", "points": 0, "criteria": [{"index": 1, "id": 227970, "desc": "Broken Throne"}, {"index": 2, "id": 227971, "desc": "Daggerspine Point"}]}, "63164": {"expansion_id": -1, "expansion": "Unknown (-1)", "points": 0, "criteria": []}, "63182": {"expansion_id": -1, "expansion": "Unknown (-1)", "points": 0, "criteria": [{"index": 1, "id": 228854, "desc": "Week 1: Reinforcements"}, {"index": 2, "id": 228855, "desc": "Week 2: Malevolent Boons"}, {"index": 3, "id": 228856, "desc": "Week 3: Embers"}, {"index": 4, "id": 228857, "desc": "Week 4: Reinforcements and Alarm Bells"}, {"index": 5, "id": 228858, "desc": "Week 5: Boons and Patrols"}, {"index": 6, "id": 228859, "desc": "Week 6: Embers and Manifestations"}]}, "63237": {"expansion_id": -1, "expansion": "Unknown (-1)", "points": 0, "criteria": []}, "63240": {"expansion_id": -1, "expansion": "Unknown (-1)", "points": 0, "criteria": []}, "63241": {"expansion_id": -1, "expansion": "Unknown (-1)", "points": 0, "criteria": []}, "63242": {"expansion_id": -1, "expansion": "Unknown (-1)", "points": 0, "criteria": []}, "63246": {"expansion_id": -1, "expansion": "Unknown (-1)", "points": 0, "criteria": []}, "63247": {"expansion_id": -1, "expansion": "Unknown (-1)", "points": 0, "criteria": []}, "63264": {"expansion_id": -1, "expansion": "Unknown (-1)", "points": 0, "criteria": [{"index": 1, "id": 229643, "desc": "Heroic: Worlds Ahead"}, {"index": 2, "id": 229644, "desc": "Heroic: Power Creep"}, {"index": 3, "id": 229645, "desc": "Heroic: Pain of Command"}, {"index": 4, "id": 229646, "desc": "Heroic Climate Strange: Val"}, {"index": 5, "id": 229647, "desc": "Heroic Climate Strange: Naigtal"}, {"index": 6, "id": 229648, "desc": "Heroic Slugger"}]}, "63325": {"expansion_id": -1, "expansion": "Unknown (-1)", "points": 0, "criteria": []}, "63343": {"expansion_id": -1, "expansion": "Unknown (-1)", "points": 0, "criteria": [{"index": 1, "id": 229493, "desc": "Goals scored"}]}, "63348": {"expansion_id": -1, "expansion": "Unknown (-1)", "points": 0, "criteria": [{"index": 1, "id": 229607, "desc": "Interminable Uarn"}, {"index": 2, "id": 229608, "desc": "Broxion"}, {"index": 3, "id": 229609, "desc": "Swalewing Matriarch"}, {"index": 4, "id": 229610, "desc": "Lomelith"}, {"index": 5, "id": 229611, "desc": "Auredar"}, {"index": 6, "id": 229612, "desc": "Warp Agent Xi'grivr"}, {"index": 7, "id": 229613, "desc": "Indomitable Mk XII"}, {"index": 8, "id": 229614, "desc": "Slaipaan"}, {"index": 9, "id": 229632, "desc": "Nelgothar"}, {"index": 10, "id": 229633, "desc": "Sleet-Rune"}, {"index": 11, "id": 229634, "desc": "Atomus"}, {"index": 12, "id": 229635, "desc": "Glacial Broodmother"}, {"index": 13, "id": 229636, "desc": "Mercilus"}, {"index": 14, "id": 229637, "desc": "Xirah"}, {"index": 15, "id": 229638, "desc": "Krilkan"}, {"index": 16, "id": 229639, "desc": "Opprimius"}, {"index": 17, "id": 229640, "desc": "The Horror Below"}, {"index": 18, "id": 229641, "desc": "Shadowguard Destroyer"}, {"index": 19, "id": 229763, "desc": "Warbringer Thal'kuur"}]}, "63349": {"expansion_id": -1, "expansion": "Unknown (-1)", "points": 0, "criteria": []}, "63383": {"expansion_id": -1, "expansion": "Unknown (-1)", "points": 0, "criteria": [{"index": 1, "id": 229859, "desc": "A Frigid Welcome to Val"}, {"index": 2, "id": 229860, "desc": "A Swampy Welcome to Naigtal"}]}, "63384": {"expansion_id": -1, "expansion": "Unknown (-1)", "points": 0, "criteria": [{"index": 1, "id": 229866, "desc": "The Road Not Taken Twice"}, {"index": 2, "id": 229867, "desc": "Spatial Reasoning"}, {"index": 3, "id": 229868, "desc": "Bouncy Mushrooms"}, {"index": 4, "id": 229869, "desc": "Aerospores"}, {"index": 5, "id": 229870, "desc": "The Grappler"}, {"index": 6, "id": 229871, "desc": "Preparing for Threats"}, {"index": 7, "id": 229887, "desc": "Exterior Manaforge Translocator"}]}, "63385": {"expansion_id": -1, "expansion": "Unknown (-1)", "points": 0, "criteria": [{"index": 1, "id": 229873, "desc": "Manaforge Reconnaissance"}, {"index": 2, "id": 229877, "desc": "Pilfered Technology"}, {"index": 3, "id": 229878, "desc": "A Cryptic Mystery"}]}, "63386": {"expansion_id": -1, "expansion": "Unknown (-1)", "points": 0, "criteria": [{"index": 1, "id": 229884, "desc": "Victory Within Hindsight"}, {"index": 2, "id": 229885, "desc": "A Shot at the Dark"}, {"index": 3, "id": 229886, "desc": "Umbral Title Bout"}]}}